{
  "is-c3-addon": true,
  "sdk-version": 2,
  "min-construct-version": "r401",
  "type": "plugin",
  "name": "Firebase_In_App_Messaging",
  "id": "EMI_INDO_Firebase_In_App_Messaging",
  "version": "1.0.0.1",
  "author": "EMI_INDO",
  "website": "https://www.construct.net/en/make-games/addons",
  "documentation": "https://github.com/chemerisuk/cordova-plugin-firebase-inappmessaging#readme",
  "description": "Firebase_In_App_Messaging",
  "editor-scripts": [
    "plugin.js",
    "type.js",
    "instance.js"
  ],
  "file-list": [
    "c3runtime/main.js",
    "c3runtime/plugin.js",
    "c3runtime/type.js",
    "c3runtime/instance.js",
    "c3runtime/conditions.js",
    "c3runtime/actions.js",
    "c3runtime/expressions.js",
    "lang/en-US.json",
    "aces.json",
    "addon.json",
    "icon.svg",
    "instance.js",
    "plugin.js",
    "type.js"
  ]
}